emqx_extension/__init__.py
emqx_extension/hooks.py
emqx_extension/states.py
emqx_extension/types.py
emqx_extension_sdk-0.2.dist-info/LICENSE
emqx_extension_sdk-0.2.dist-info/METADATA
emqx_extension_sdk-0.2.dist-info/WHEEL
emqx_extension_sdk-0.2.dist-info/top_level.txt
emqx_extension_sdk-0.2.dist-info/RECORD
