Metadata-Version: 2.1
Name: emqx-extension-sdk
Version: 0.2
Summary: The Python SDK For EMQ X Extension
Home-page: https://github.com/emqx/emqx-python-sdk
Author: EMQ X
Author-email: taodk@emqx.io
License: Apache License 2.0
Keywords: emqx,IoT,MQTT,MQTT SDK,emqx-extension
Platform: any
Requires-Python: >=3.6.0
